init_admin_command/__init__.py
init_admin_command/management/__init__.py
init_admin_command/management/commands/__init__.py
init_admin_command/management/commands/initadmin.py
django_init_admin_command-0.1.0.dist-info/LICENSE
django_init_admin_command-0.1.0.dist-info/METADATA
django_init_admin_command-0.1.0.dist-info/WHEEL
django_init_admin_command-0.1.0.dist-info/top_level.txt
django_init_admin_command-0.1.0.dist-info/RECORD
