Metadata-Version: 2.1
Name: django-init-admin-command
Version: 0.1.0
Summary: A Django admin command to create an admin user if no user exists
Home-page: https://github.com/gri38/django_init_admin
Author: gri38
Author-email: onzeweb@zaclys.net
Classifier: Intended Audience :: Developers
Classifier: Operating System :: OS Independent
Classifier: Programming Language :: Python
Classifier: Programming Language :: Python :: 3
Classifier: Topic :: Software Development :: Libraries :: Python Modules
License-File: LICENSE
Requires-Dist: Django (>=2.2)
